{
    "openlabel": {
        "metadata": {
            "schema_version": "1.0.0"
        },
        "coordinate_systems": 663,
        "frames": {
            "663": {
                "objects": {
                    "0": {
                        "object_data": {
                            "name": "CAR_0",
                            "type": "CAR",
                            "bbox": [
                                {
                                    "name": "full_bbox",
                                    "val": [
                                        223,
                                        40,
                                        48,
                                        43
                                    ],
                                    "attributes": {
                                        "text": [
                                            {
                                                "name": "sensor_id",
                                                "val": "default_cam"
                                            }
                                        ]
                                    }
                                }
                            ]
                        }
                    },
                    "1": {
                        "object_data": {
                            "name": "CAR_1",
                            "type": "CAR",
                            "bbox": [
                                {
                                    "name": "full_bbox",
                                    "val": [
                                        294,
                                        18,
                                        39,
                                        37
                                    ],
                                    "attributes": {
                                        "text": [
                                            {
                                                "name": "sensor_id",
                                                "val": "default_cam"
                                            }
                                        ]
                                    }
                                }
                            ]
                        }
                    },
                    "2": {
                        "object_data": {
                            "name": "CAR_2",
                            "type": "CAR",
                            "bbox": [
                                {
                                    "name": "full_bbox",
                                    "val": [
                                        180,
                                        57,
                                        53,
                                        49
                                    ],
                                    "attributes": {
                                        "text": [
                                            {
                                                "name": "sensor_id",
                                                "val": "default_cam"
                                            }
                                        ]
                                    }
                                }
                            ]
                        }
                    },
                    "3": {
                        "object_data": {
                            "name": "CAR_3",
                            "type": "CAR",
                            "bbox": [
                                {
                                    "name": "full_bbox",
                                    "val": [
                                        206,
                                        61,
                                        61,
                                        54
                                    ],
                                    "attributes": {
                                        "text": [
                                            {
                                                "name": "sensor_id",
                                                "val": "default_cam"
                                            }
                                        ]
                                    }
                                }
                            ]
                        }
                    }
                }
            }
        }
    }
}