{
    "openlabel": {
        "metadata": {
            "schema_version": "1.0.0"
        },
        "coordinate_systems": 2280,
        "frames": {
            "2280": {
                "objects": {
                    "0": {
                        "object_data": {
                            "name": "CAR_0",
                            "type": "CAR",
                            "bbox": [
                                {
                                    "name": "full_bbox",
                                    "val": [
                                        280,
                                        24,
                                        43,
                                        39
                                    ],
                                    "attributes": {
                                        "text": [
                                            {
                                                "name": "sensor_id",
                                                "val": "default_cam"
                                            }
                                        ]
                                    }
                                }
                            ]
                        }
                    },
                    "1": {
                        "object_data": {
                            "name": "TRUCK_1",
                            "type": "TRUCK",
                            "bbox": [
                                {
                                    "name": "full_bbox",
                                    "val": [
                                        377,
                                        19,
                                        43,
                                        38
                                    ],
                                    "attributes": {
                                        "text": [
                                            {
                                                "name": "sensor_id",
                                                "val": "default_cam"
                                            }
                                        ]
                                    }
                                }
                            ]
                        }
                    },
                    "2": {
                        "object_data": {
                            "name": "CAR_2",
                            "type": "CAR",
                            "bbox": [
                                {
                                    "name": "full_bbox",
                                    "val": [
                                        212,
                                        192,
                                        102,
                                        103
                                    ],
                                    "attributes": {
                                        "text": [
                                            {
                                                "name": "sensor_id",
                                                "val": "default_cam"
                                            }
                                        ]
                                    }
                                }
                            ]
                        }
                    },
                    "3": {
                        "object_data": {
                            "name": "CAR_3",
                            "type": "CAR",
                            "bbox": [
                                {
                                    "name": "full_bbox",
                                    "val": [
                                        355,
                                        82,
                                        50,
                                        51
                                    ],
                                    "attributes": {
                                        "text": [
                                            {
                                                "name": "sensor_id",
                                                "val": "default_cam"
                                            }
                                        ]
                                    }
                                }
                            ]
                        }
                    },
                    "4": {
                        "object_data": {
                            "name": "CAR_4",
                            "type": "CAR",
                            "bbox": [
                                {
                                    "name": "full_bbox",
                                    "val": [
                                        380,
                                        42,
                                        41,
                                        43
                                    ],
                                    "attributes": {
                                        "text": [
                                            {
                                                "name": "sensor_id",
                                                "val": "default_cam"
                                            }
                                        ]
                                    }
                                }
                            ]
                        }
                    },
                    "5": {
                        "object_data": {
                            "name": "CAR_5",
                            "type": "CAR",
                            "bbox": [
                                {
                                    "name": "full_bbox",
                                    "val": [
                                        157,
                                        75,
                                        76,
                                        69
                                    ],
                                    "attributes": {
                                        "text": [
                                            {
                                                "name": "sensor_id",
                                                "val": "default_cam"
                                            }
                                        ]
                                    }
                                }
                            ]
                        }
                    }
                }
            }
        }
    }
}