{
    "openlabel": {
        "metadata": {
            "schema_version": "1.0.0"
        },
        "coordinate_systems": 816,
        "frames": {
            "816": {
                "objects": {
                    "0": {
                        "object_data": {
                            "name": "CAR_0",
                            "type": "CAR",
                            "bbox": [
                                {
                                    "name": "full_bbox",
                                    "val": [
                                        373,
                                        13,
                                        36,
                                        27
                                    ],
                                    "attributes": {
                                        "text": [
                                            {
                                                "name": "sensor_id",
                                                "val": "default_cam"
                                            }
                                        ]
                                    }
                                }
                            ]
                        }
                    },
                    "1": {
                        "object_data": {
                            "name": "CAR_1",
                            "type": "CAR",
                            "bbox": [
                                {
                                    "name": "full_bbox",
                                    "val": [
                                        305,
                                        89,
                                        58,
                                        59
                                    ],
                                    "attributes": {
                                        "text": [
                                            {
                                                "name": "sensor_id",
                                                "val": "default_cam"
                                            }
                                        ]
                                    }
                                }
                            ]
                        }
                    },
                    "2": {
                        "object_data": {
                            "name": "TRAILER_2",
                            "type": "TRAILER",
                            "bbox": [
                                {
                                    "name": "full_bbox",
                                    "val": [
                                        355,
                                        27,
                                        51,
                                        54
                                    ],
                                    "attributes": {
                                        "text": [
                                            {
                                                "name": "sensor_id",
                                                "val": "default_cam"
                                            }
                                        ]
                                    }
                                }
                            ]
                        }
                    },
                    "3": {
                        "object_data": {
                            "name": "CAR_3",
                            "type": "CAR",
                            "bbox": [
                                {
                                    "name": "full_bbox",
                                    "val": [
                                        195,
                                        186,
                                        119,
                                        119
                                    ],
                                    "attributes": {
                                        "text": [
                                            {
                                                "name": "sensor_id",
                                                "val": "default_cam"
                                            }
                                        ]
                                    }
                                }
                            ]
                        }
                    }
                }
            }
        }
    }
}