{
    "openlabel": {
        "metadata": {
            "schema_version": "1.0.0"
        },
        "coordinate_systems": 975,
        "frames": {
            "975": {
                "objects": {
                    "0": {
                        "object_data": {
                            "name": "CAR_0",
                            "type": "CAR",
                            "bbox": [
                                {
                                    "name": "full_bbox",
                                    "val": [
                                        263,
                                        130,
                                        71,
                                        70
                                    ],
                                    "attributes": {
                                        "text": [
                                            {
                                                "name": "sensor_id",
                                                "val": "default_cam"
                                            }
                                        ]
                                    }
                                }
                            ]
                        }
                    },
                    "1": {
                        "object_data": {
                            "name": "BUS_1",
                            "type": "BUS",
                            "bbox": [
                                {
                                    "name": "full_bbox",
                                    "val": [
                                        237,
                                        24,
                                        86,
                                        48
                                    ],
                                    "attributes": {
                                        "text": [
                                            {
                                                "name": "sensor_id",
                                                "val": "default_cam"
                                            }
                                        ]
                                    }
                                }
                            ]
                        }
                    },
                    "2": {
                        "object_data": {
                            "name": "CAR_2",
                            "type": "CAR",
                            "bbox": [
                                {
                                    "name": "full_bbox",
                                    "val": [
                                        286,
                                        21,
                                        41,
                                        37
                                    ],
                                    "attributes": {
                                        "text": [
                                            {
                                                "name": "sensor_id",
                                                "val": "default_cam"
                                            }
                                        ]
                                    }
                                }
                            ]
                        }
                    },
                    "3": {
                        "object_data": {
                            "name": "CAR_3",
                            "type": "CAR",
                            "bbox": [
                                {
                                    "name": "full_bbox",
                                    "val": [
                                        364,
                                        19,
                                        37,
                                        36
                                    ],
                                    "attributes": {
                                        "text": [
                                            {
                                                "name": "sensor_id",
                                                "val": "default_cam"
                                            }
                                        ]
                                    }
                                }
                            ]
                        }
                    },
                    "4": {
                        "object_data": {
                            "name": "CAR_4",
                            "type": "CAR",
                            "bbox": [
                                {
                                    "name": "full_bbox",
                                    "val": [
                                        330,
                                        59,
                                        45,
                                        47
                                    ],
                                    "attributes": {
                                        "text": [
                                            {
                                                "name": "sensor_id",
                                                "val": "default_cam"
                                            }
                                        ]
                                    }
                                }
                            ]
                        }
                    }
                }
            }
        }
    }
}