{
    "openlabel": {
        "metadata": {
            "schema_version": "1.0.0"
        },
        "coordinate_systems": 159,
        "frames": {
            "159": {
                "objects": {
                    "0": {
                        "object_data": {
                            "name": "TRAILER_0",
                            "type": "TRAILER",
                            "bbox": [
                                {
                                    "name": "full_bbox",
                                    "val": [
                                        493,
                                        139,
                                        240,
                                        170
                                    ],
                                    "attributes": {
                                        "text": [
                                            {
                                                "name": "sensor_id",
                                                "val": "default_cam"
                                            }
                                        ]
                                    }
                                }
                            ]
                        }
                    },
                    "1": {
                        "object_data": {
                            "name": "CAR_1",
                            "type": "CAR",
                            "bbox": [
                                {
                                    "name": "full_bbox",
                                    "val": [
                                        377,
                                        15,
                                        34,
                                        30
                                    ],
                                    "attributes": {
                                        "text": [
                                            {
                                                "name": "sensor_id",
                                                "val": "default_cam"
                                            }
                                        ]
                                    }
                                }
                            ]
                        }
                    },
                    "2": {
                        "object_data": {
                            "name": "CAR_2",
                            "type": "CAR",
                            "bbox": [
                                {
                                    "name": "full_bbox",
                                    "val": [
                                        361,
                                        40,
                                        41,
                                        41
                                    ],
                                    "attributes": {
                                        "text": [
                                            {
                                                "name": "sensor_id",
                                                "val": "default_cam"
                                            }
                                        ]
                                    }
                                }
                            ]
                        }
                    },
                    "3": {
                        "object_data": {
                            "name": "CAR_3",
                            "type": "CAR",
                            "bbox": [
                                {
                                    "name": "full_bbox",
                                    "val": [
                                        299,
                                        17,
                                        41,
                                        35
                                    ],
                                    "attributes": {
                                        "text": [
                                            {
                                                "name": "sensor_id",
                                                "val": "default_cam"
                                            }
                                        ]
                                    }
                                }
                            ]
                        }
                    },
                    "4": {
                        "object_data": {
                            "name": "TRUCK_4",
                            "type": "TRUCK",
                            "bbox": [
                                {
                                    "name": "full_bbox",
                                    "val": [
                                        362,
                                        129,
                                        89,
                                        134
                                    ],
                                    "attributes": {
                                        "text": [
                                            {
                                                "name": "sensor_id",
                                                "val": "default_cam"
                                            }
                                        ]
                                    }
                                }
                            ]
                        }
                    },
                    "5": {
                        "object_data": {
                            "name": "BUS_5",
                            "type": "BUS",
                            "bbox": [
                                {
                                    "name": "full_bbox",
                                    "val": [
                                        142,
                                        102,
                                        59,
                                        102
                                    ],
                                    "attributes": {
                                        "text": [
                                            {
                                                "name": "sensor_id",
                                                "val": "default_cam"
                                            }
                                        ]
                                    }
                                }
                            ]
                        }
                    }
                }
            }
        }
    }
}